odoo10_addon_hr_recruitment_skill-10.0.1.0.0-py2.7-nspkg.pth
odoo/addons/hr_recruitment_skill/README.rst
odoo/addons/hr_recruitment_skill/__init__.py
odoo/addons/hr_recruitment_skill/__manifest__.py
odoo/addons/hr_recruitment_skill/i18n/fr.po
odoo/addons/hr_recruitment_skill/i18n/hr_recruitment_skill.pot
odoo/addons/hr_recruitment_skill/models/__init__.py
odoo/addons/hr_recruitment_skill/models/hr_job.py
odoo/addons/hr_recruitment_skill/views/hr_recruitment_skill.xml
odoo10_addon_hr_recruitment_skill-10.0.1.0.0.dist-info/DESCRIPTION.rst
odoo10_addon_hr_recruitment_skill-10.0.1.0.0.dist-info/METADATA
odoo10_addon_hr_recruitment_skill-10.0.1.0.0.dist-info/RECORD
odoo10_addon_hr_recruitment_skill-10.0.1.0.0.dist-info/WHEEL
odoo10_addon_hr_recruitment_skill-10.0.1.0.0.dist-info/metadata.json
odoo10_addon_hr_recruitment_skill-10.0.1.0.0.dist-info/namespace_packages.txt
odoo10_addon_hr_recruitment_skill-10.0.1.0.0.dist-info/top_level.txt
